zero_sql/__init__.py
zero_sql/engine.py
zero_sql-0.1.0.dist-info/LICENSE
zero_sql-0.1.0.dist-info/METADATA
zero_sql-0.1.0.dist-info/WHEEL
zero_sql-0.1.0.dist-info/top_level.txt
zero_sql-0.1.0.dist-info/RECORD
