Metadata-Version: 2.1
Name: zero-sql
Version: 0.1.0
Summary: A SQL-less lightweight Python DB layer
Author: ABINAYA SAKTHIVEL
Author-email: abisakthivel8@gmail.com
License: MIT
Keywords: database sql abstraction sqlite
Classifier: Programming Language :: Python :: 3
Classifier: License :: OSI Approved :: MIT License
Classifier: Operating System :: OS Independent
Requires-Python: >=3.6
License-File: LICENSE
